post_type_discovery/__init__.py
post_type_discovery/main.py
post_type_discovery-1.0.0.dist-info/LICENSE.md
post_type_discovery-1.0.0.dist-info/METADATA
post_type_discovery-1.0.0.dist-info/WHEEL
post_type_discovery-1.0.0.dist-info/top_level.txt
post_type_discovery-1.0.0.dist-info/RECORD
