Metadata-Version: 2.1
Name: post-type-discovery
Version: 1.0.0
Summary: Find the post type associated with a web page in accordance with the Post Type Discovery algorithm.
Home-page: https://github.com/capjamesg/post-type-discovery
Author: capjamesg
Author-email: jamesg@jamesg.blog
License: UNKNOWN
Project-URL: Bug Tracker, https://github.com/capjamesg/post-type-discovery/issues
Platform: UNKNOWN
Classifier: Programming Language :: Python :: 3
Classifier: License :: OSI Approved :: MIT License
Classifier: Operating System :: OS Independent
Requires-Python: >=3.6
License-File: LICENSE.md
